cdp_chrome_tabs/__init__.py
cdp_chrome_tabs/chrome_tabs.py
cdp_chrome_tabs-0.1.0.dist-info/licenses/LICENSE
cdp_chrome_tabs-0.1.0.dist-info/METADATA
cdp_chrome_tabs-0.1.0.dist-info/WHEEL
cdp_chrome_tabs-0.1.0.dist-info/top_level.txt
cdp_chrome_tabs-0.1.0.dist-info/RECORD
