Metadata-Version: 2.4
Name: cdp-chrome-tabs
Version: 0.1.0
Summary: A Python package to interact with Chrome tabs via Chrome DevTools Protocol
Home-page: https://github.com/guocity/cdp-chrome-tabs
Author: guocity
Author-email: your.email@example.com
Keywords: chrome,browser,devtools,automation,cdp
Classifier: Programming Language :: Python :: 3
Classifier: License :: OSI Approved :: MIT License
Classifier: Operating System :: OS Independent
Requires-Python: >=3.6
License-File: LICENSE
Requires-Dist: requests
Dynamic: author
Dynamic: author-email
Dynamic: classifier
Dynamic: description
Dynamic: description-content-type
Dynamic: home-page
Dynamic: keywords
Dynamic: license-file
Dynamic: requires-dist
Dynamic: requires-python
Dynamic: summary
